lemniscat/core/contract/__init__.py
lemniscat/core/contract/engine_contract.py
lemniscat/core/model/__init__.py
lemniscat/core/model/models.py
lemniscat/core/util/__init__.py
lemniscat/core/util/helpers.py
lemniscat.core-0.3.1.dist-info/LICENSE
lemniscat.core-0.3.1.dist-info/METADATA
lemniscat.core-0.3.1.dist-info/WHEEL
lemniscat.core-0.3.1.dist-info/top_level.txt
lemniscat.core-0.3.1.dist-info/RECORD
